automated_walk_bike_counter/__init__.py
automated_walk_bike_counter/_version.py
automated_walk_bike_counter/core/__init__.py
automated_walk_bike_counter/core/configuration.py
automated_walk_bike_counter/core/frame.py
automated_walk_bike_counter/core/functions.py
automated_walk_bike_counter/core/main.py
automated_walk_bike_counter/core/model.py
automated_walk_bike_counter/core/movingobject.py
automated_walk_bike_counter/core/bounding_box/__init__.py
automated_walk_bike_counter/core/bounding_box/biker.py
automated_walk_bike_counter/core/bounding_box/bus.py
automated_walk_bike_counter/core/bounding_box/car.py
automated_walk_bike_counter/core/bounding_box/detected_object.py
automated_walk_bike_counter/core/bounding_box/motorbiker.py
automated_walk_bike_counter/core/bounding_box/pedestrian.py
automated_walk_bike_counter/core/bounding_box/truck.py
automated_walk_bike_counter/core/data/coco.names
automated_walk_bike_counter/core/data/yolo_anchors.txt
automated_walk_bike_counter/core/tracking/__init__.py
automated_walk_bike_counter/core/tracking/counter.py
automated_walk_bike_counter/core/tracking/object_tracker.py
automated_walk_bike_counter/gui/__init__.py
automated_walk_bike_counter/gui/app.py
automated_walk_bike_counter/gui/video.py
automated_walk_bike_counter/gui/controller/__init__.py
automated_walk_bike_counter/gui/controller/base.py
automated_walk_bike_counter/gui/controller/main_controller.py
automated_walk_bike_counter/gui/model/__init__.py
automated_walk_bike_counter/gui/model/base.py
automated_walk_bike_counter/gui/model/main_model.py
automated_walk_bike_counter/gui/static/images/loading.gif
automated_walk_bike_counter/gui/static/videos/sample.mp4
automated_walk_bike_counter/gui/utility/__init__.py
automated_walk_bike_counter/gui/view/__init__.py
automated_walk_bike_counter/gui/view/base.py
automated_walk_bike_counter/gui/view/main.py
automated_walk_bike_counter/gui/widgets/__init__.py
automated_walk_bike_counter/gui/widgets/aoi.py
automated_walk_bike_counter-0.1.0.dist-info/LICENSE
automated_walk_bike_counter-0.1.0.dist-info/METADATA
automated_walk_bike_counter-0.1.0.dist-info/WHEEL
automated_walk_bike_counter-0.1.0.dist-info/entry_points.txt
automated_walk_bike_counter-0.1.0.dist-info/top_level.txt
automated_walk_bike_counter-0.1.0.dist-info/RECORD
