Metadata-Version: 2.1
Name: automated-walk-bike-counter
Version: 0.1.0
Summary: A computer vision application for automated countingof pedestrians and cyclists
Home-page: https://github.com/CityOfLosAngeles/automated-walk-bike-counter
Maintainer: CSULA and Los Angeles ITA
Maintainer-email: 
License: Apache-2.0 license
Keywords: computer vision,city,streets,traffic,pedestrian,cyclist
Platform: UNKNOWN
Requires-Dist: tensorflow (<2)
Requires-Dist: opencv-python
Requires-Dist: munkres
Requires-Dist: pykalman
Requires-Dist: pillow
Requires-Dist: tqdm
Requires-Dist: fsspec (>=0.7.3)
Requires-Dist: requests
Requires-Dist: configargparse
Requires-Dist: s3fs (==0.3.5)
Provides-Extra: develop
Requires-Dist: pre-commit ; extra == 'develop'
Requires-Dist: flake8 ; extra == 'develop'
Requires-Dist: black ; extra == 'develop'
Requires-Dist: isort ; extra == 'develop'
Provides-Extra: gpu
Requires-Dist: tensorflow-gpu ; extra == 'gpu'
